{
  "Swagger.UI.EndpointName": "Gerit v1",
  "Swagger.UI.DocumentTitle": "Gerit API",
  "Swagger.Api.Title": "Gerit API",
  "Swagger.Api.Title.Development": "Gerit API - Development",
  "Swagger.Api.Title.Staging": "Gerit API - Staging",
  "Swagger.Api.Title.Production": "Gerit API - Production",
  "Swagger.Api.Description": "Gerit authentication and authorization API",
  "Swagger.Api.Description.Development": "Gerit authentication and authorization API - Development Environment",
  "Swagger.Api.Description.Staging": "Gerit authentication and authorization API - Staging Environment",
  "Swagger.Api.Description.Production": "Gerit authentication and authorization API - Production Environment",
  "Swagger.Api.Contact.Name": "VianaHub Support",
  "Swagger.Api.License.Name": "Proprietary",

  "Swagger.Security.Bearer.Description": "JWT Authorization header using the Bearer scheme. Enter 'Bearer' [space] followed by your token in the field below.",

  "Swagger.Tag.Health": "Health",
  "Swagger.Tag.Actions": "Actions",
  "Swagger.Tag.Resources": "Resources",
  "Swagger.Tag.Roles": "Roles",
  "Swagger.Tag.Plans": "Plans",
  "Swagger.Tag.Tenants": "Tenants",
  "Swagger.Tag.Users": "Users",
  "Swagger.Tag.UserPreferences": "User Preferences",
  "Swagger.Tag.Subscriptions": "Subscriptions",
  "Swagger.Tag.UserRoles": "User-Role Associations",
  "Swagger.Tag.RolePermissions": "Role Permissions",
  "Swagger.Tag.JobDefinitions": "Job Definitions",
  "Swagger.Tag.JwtKeys": "JWT Keys",
  "Swagger.Tag.Functions": "Functions",
  "Swagger.Tag.Equipments": "Equipments",
  "Swagger.Tag.EquipmentTypes": "Equipment Types",
  "Swagger.Tag.Vehicles": "Vehicles",
  "Swagger.Tag.Teams": "Teams",
  "Swagger.Tag.TeamMembers": "Team Members",
  "Swagger.Tag.TeamMembersTeams": "Team-Member Associations",
  "Swagger.Tag.TeamMemberAddresses": "Team Member Addresses",
  "Swagger.Tag.TeamMemberContacts": "Team Member Contacts",
  "Swagger.Tag.Auth": "Authentication",
  "Swagger.Tag.AddressTypes": "Address Types",
  "Swagger.Tag.FileTypes": "File Types",
  "Swagger.Tag.OriginTypes": "Origin Types",
  "Swagger.Tag.AttachmentCategories": "Attachment Categories",
  "Swagger.Tag.Clients": "Clients",
  "Swagger.Tag.ClientTypes": "Client Types",
  "Swagger.Tag.ConsentTypes": "Consent Types",
  "Swagger.Tag.ClientAddresses": "Client Addresses",
  "Swagger.Tag.ClientContacts": "Client Contacts",
  "Swagger.Tag.ClientCompanies": "Client Companies",
  "Swagger.Tag.ClientIndividuals": "Clients Individual",
  "Swagger.Tag.ClientFiscalData": "Client Fiscal Data",
  "Swagger.Tag.ClientConsents": "Client Consents",
  "Swagger.Tag.ClientHierarchies": "Client Hierarchies",
  "Swagger.Tag.Employees": "Employees",
  "Swagger.Tag.EmployeeAddresses": "Employee Addresses",
  "Swagger.Tag.EmployeeContacts": "Employee Contacts",
  "Swagger.Tag.EmployeeTeams": "Employee Teams",
  "Swagger.Tag.Status": "Statuses",
  "Swagger.Tag.StatusTypes": "Status Types",
  "Swagger.Tag.Visits": "Visits",
  "Swagger.Tag.VisitAddresses": "Visit Addresses",
  "Swagger.Tag.VisitContacts": "Visit Contacts",
  "Swagger.Tag.VisitAttachments": "Visit Attachments",
  "Swagger.Tag.VisitTeams": "Visit Teams",
  "Swagger.Tag.VisitTeamEmployees": "Visit Team Employees",
  "Swagger.Tag.VisitTeamEquipments": "Visit Team Equipments",
  "Swagger.Tag.VisitTeamVehicles": "Visit Team Vehicles",
  "Swagger.Tag.Jobs": "Jobs",



  "Swagger.Endpoint.HealthCheck.Summary": "Health Check",
  "Swagger.Endpoint.HealthCheck.Description": "Checks if the API is working correctly",

  "Swagger.Endpoint.Auth.Register.Summary": "Register new user",
  "Swagger.Endpoint.Auth.Login.Summary": "Perform login",
  "Swagger.Endpoint.Auth.Refresh.Summary": "Refresh access token",
  "Swagger.Endpoint.Auth.Tenant.Summary": "Get available tenants",

  "Swagger.Endpoint.Action.GetAll.Summary": "Get all actions",
  "Swagger.Endpoint.Action.GetPaged.Summary": "Get paged actions",
  "Swagger.Endpoint.Action.GetById.Summary": "Get action by ID",
  "Swagger.Endpoint.Action.Create.Summary": "Create new action",
  "Swagger.Endpoint.Action.Update.Summary": "Update action",
  "Swagger.Endpoint.Action.Delete.Summary": "Delete action",
  "Swagger.Endpoint.Action.Activate.Summary": "Activate action",
  "Swagger.Endpoint.Action.Deactivate.Summary": "Deactivate action",
  "Swagger.Endpoint.Action.BulkUpload.Summary": "Bulk upload actions",

  "Swagger.Endpoint.Resource.GetAll.Summary": "Get all resources",
  "Swagger.Endpoint.Resource.GetPaged.Summary": "Get paged resources",
  "Swagger.Endpoint.Resource.GetById.Summary": "Get resource by ID",
  "Swagger.Endpoint.Resource.Create.Summary": "Create new resource",
  "Swagger.Endpoint.Resource.Update.Summary": "Update resource",
  "Swagger.Endpoint.Resource.Delete.Summary": "Delete resource",
  "Swagger.Endpoint.Resource.Activate.Summary": "Activate resource",
  "Swagger.Endpoint.Resource.Deactivate.Summary": "Deactivate resource",
  "Swagger.Endpoint.Resource.BulkUpload.Summary": "Bulk upload resources",

  "Swagger.Endpoint.Function.GetAll.Summary": "Get all functions",
  "Swagger.Endpoint.Function.GetById.Summary": "Get function by ID",
  "Swagger.Endpoint.Function.GetPaged.Summary": "Get functions paged",
  "Swagger.Endpoint.Function.Create.Summary": "Create new function",
  "Swagger.Endpoint.Function.Update.Summary": "Update function",
  "Swagger.Endpoint.Function.Activate.Summary": "Activate function",
  "Swagger.Endpoint.Function.Deactivate.Summary": "Deactivate function",
  "Swagger.Endpoint.Function.Delete.Summary": "Delete function",
  "Swagger.Endpoint.Function.BulkUpload.Summary": "Bulk upload functions",

  "Swagger.Endpoint.Vehicle.GetAll.Summary": "Get all vehicles",
  "Swagger.Endpoint.Vehicle.GetPaged.Summary": "Get vehicles paged",
  "Swagger.Endpoint.Vehicle.GetById.Summary": "Get vehicle by ID",
  "Swagger.Endpoint.Vehicle.Create.Summary": "Create new vehicle",
  "Swagger.Endpoint.Vehicle.Update.Summary": "Update vehicle",
  "Swagger.Endpoint.Vehicle.Delete.Summary": "Delete vehicle",
  "Swagger.Endpoint.Vehicle.Activate.Summary": "Activate vehicle",
  "Swagger.Endpoint.Vehicle.Deactivate.Summary": "Deactivate vehicle",
  "Swagger.Endpoint.Vehicle.BulkUpload.Summary": "Bulk upload vehicles",

  "Swagger.Endpoint.TeamMember.GetAll.Summary": "Get all team members",
  "Swagger.Endpoint.TeamMember.GetPaged.Summary": "Get team members paged",
  "Swagger.Endpoint.TeamMember.GetById.Summary": "Get team member by ID",
  "Swagger.Endpoint.TeamMember.Create.Summary": "Create new team member",
  "Swagger.Endpoint.TeamMember.Update.Summary": "Update team member",
  "Swagger.Endpoint.TeamMember.Delete.Summary": "Delete team member",
  "Swagger.Endpoint.TeamMember.Activate.Summary": "Activate team member",
  "Swagger.Endpoint.TeamMember.Deactivate.Summary": "Deactivate team member",
  "Swagger.Endpoint.TeamMember.BulkUpload.Summary": "Bulk upload team members",

  "Swagger.Endpoint.TeamMemberAddress.GetAll.Summary": "Get all team member addresses",
  "Swagger.Endpoint.TeamMemberAddress.GetPaged.Summary": "Get team member addresses paged",
  "Swagger.Endpoint.TeamMemberAddress.GetById.Summary": "Get team member address by ID",
  "Swagger.Endpoint.TeamMemberAddress.Create.Summary": "Create new team member address",
  "Swagger.Endpoint.TeamMemberAddress.Update.Summary": "Update team member address",
  "Swagger.Endpoint.TeamMemberAddress.Delete.Summary": "Delete team member address",
  "Swagger.Endpoint.TeamMemberAddress.Activate.Summary": "Activate team member address",
  "Swagger.Endpoint.TeamMemberAddress.Deactivate.Summary": "Deactivate team member address",
  "Swagger.Endpoint.TeamMemberAddress.BulkUpload.Summary": "Bulk upload team member addresses",

  "Swagger.Endpoint.TeamMemberContact.GetAll.Summary": "Get all team member contacts",
  "Swagger.Endpoint.TeamMemberContact.GetPaged.Summary": "Get team member contacts paged",
  "Swagger.Endpoint.TeamMemberContact.GetById.Summary": "Get team member contact by ID",
  "Swagger.Endpoint.TeamMemberContact.Create.Summary": "Create new team member contact",
  "Swagger.Endpoint.TeamMemberContact.Update.Summary": "Update team member contact",
  "Swagger.Endpoint.TeamMemberContact.Delete.Summary": "Delete team member contact",
  "Swagger.Endpoint.TeamMemberContact.Activate.Summary": "Activate team member contact",
  "Swagger.Endpoint.TeamMemberContact.Deactivate.Summary": "Deactivate team member contact",
  "Swagger.Endpoint.TeamMemberContact.BulkUpload.Summary": "Bulk upload team member contacts",

  "Swagger.Endpoint.Role.GetAll.Summary": "Get all roles",
  "Swagger.Endpoint.Role.GetPaged.Summary": "Get paged roles",
  "Swagger.Endpoint.Role.GetById.Summary": "Get role by ID",
  "Swagger.Endpoint.Role.Create.Summary": "Create new role",
  "Swagger.Endpoint.Role.Update.Summary": "Update role",
  "Swagger.Endpoint.Role.Delete.Summary": "Delete role",
  "Swagger.Endpoint.Role.Activate.Summary": "Activate role",
  "Swagger.Endpoint.Role.Deactivate.Summary": "Deactivate role",
  "Swagger.Endpoint.Role.BulkUpload.Summary": "Bulk upload roles",

  "Swagger.Endpoint.Plan.GetAll.Summary": "Get all plans",
  "Swagger.Endpoint.Plan.GetPaged.Summary": "Get paged plans",
  "Swagger.Endpoint.Plan.GetById.Summary": "Get plan by ID",
  "Swagger.Endpoint.Plan.Create.Summary": "Create new plan",
  "Swagger.Endpoint.Plan.Update.Summary": "Update plan",
  "Swagger.Endpoint.Plan.Delete.Summary": "Delete plan",
  "Swagger.Endpoint.Plan.Activate.Summary": "Activate plan",
  "Swagger.Endpoint.Plan.Deactivate.Summary": "Deactivate plan",
  "Swagger.Endpoint.Plan.BulkUpload.Summary": "Bulk upload plans",

  "Swagger.Endpoint.Tenant.GetAll.Summary": "Get all tenants",
  "Swagger.Endpoint.Tenant.GetPaged.Summary": "Get paged tenants",
  "Swagger.Endpoint.Tenant.GetById.Summary": "Get tenant by ID",
  "Swagger.Endpoint.Tenant.Create.Summary": "Create new tenant",
  "Swagger.Endpoint.Tenant.Update.Summary": "Update tenant",
  "Swagger.Endpoint.Tenant.Delete.Summary": "Delete tenant",
  "Swagger.Endpoint.Tenant.Activate.Summary": "Activate tenant",
  "Swagger.Endpoint.Tenant.Deactivate.Summary": "Deactivate tenant",
  "Swagger.Endpoint.Tenant.BulkUpload.Summary": "Bulk upload tenants",

  "Swagger.Endpoint.Subscription.GetAll.Summary": "Get all subscriptions",
  "Swagger.Endpoint.Subscription.GetPaged.Summary": "Get paged subscriptions",
  "Swagger.Endpoint.Subscription.GetById.Summary": "Get subscription by ID",
  "Swagger.Endpoint.Subscription.GetByTenantId.Summary": "Get subscription by tenant ID",
  "Swagger.Endpoint.Subscription.GetActive.Summary": "Get active subscriptions",
  "Swagger.Endpoint.Subscription.GetExpiring.Summary": "Get expiring subscriptions",
  "Swagger.Endpoint.Subscription.Create.Summary": "Create new subscription",
  "Swagger.Endpoint.Subscription.Update.Summary": "Update subscription",
  "Swagger.Endpoint.Subscription.Activate.Summary": "Activate subscription",
  "Swagger.Endpoint.Subscription.Deactivate.Summary": "Deactivate subscription",
  "Swagger.Endpoint.Subscription.Cancel.Summary": "Cancel subscription",
  "Swagger.Endpoint.Subscription.Renew.Summary": "Renew subscription",
  "Swagger.Endpoint.Subscription.Delete.Summary": "Delete subscription",
  "Swagger.Endpoint.Subscription.BulkUpload.Summary": "Bulk upload subscriptions",

  "Swagger.Endpoint.Equipment.GetAll.Summary": "Get all equipments",
  "Swagger.Endpoint.Equipment.GetById.Summary": "Get equipment by ID",
  "Swagger.Endpoint.Equipment.GetPaged.Summary": "Get equipments paged",
  "Swagger.Endpoint.Equipment.Create.Summary": "Create new equipment",
  "Swagger.Endpoint.Equipment.Update.Summary": "Update equipment",
  "Swagger.Endpoint.Equipment.Activate.Summary": "Activate equipment",
  "Swagger.Endpoint.Equipment.Deactivate.Summary": "Deactivate equipment",
  "Swagger.Endpoint.Equipment.Delete.Summary": "Delete equipment",
  "Swagger.Endpoint.Equipment.BulkUpload.Summary": "Bulk upload equipments",

  "Swagger.Endpoint.EquipmentType.GetAll.Summary": "Get all equipment types",
  "Swagger.Endpoint.EquipmentType.GetById.Summary": "Get equipment type by ID",
  "Swagger.Endpoint.EquipmentType.GetPaged.Summary": "Get paged equipment types",
  "Swagger.Endpoint.EquipmentType.Create.Summary": "Create new equipment type",
  "Swagger.Endpoint.EquipmentType.Update.Summary": "Update equipment type",
  "Swagger.Endpoint.EquipmentType.Activate.Summary": "Activate equipment type",
  "Swagger.Endpoint.EquipmentType.Deactivate.Summary": "Deactivate equipment type",
  "Swagger.Endpoint.EquipmentType.Delete.Summary": "Delete equipment type",
  "Swagger.Endpoint.EquipmentType.BulkUpload.Summary": "Bulk upload equipment types via CSV",

  "Swagger.Endpoint.User.GetAll.Summary": "Get all users",
  "Swagger.Endpoint.User.GetPaged.Summary": "Get paged users",
  "Swagger.Endpoint.User.GetById.Summary": "Get user by ID",
  "Swagger.Endpoint.User.Create.Summary": "Create new user",
  "Swagger.Endpoint.User.Update.Summary": "Update user",
  "Swagger.Endpoint.User.UpdatePassword.Summary": "Update user password",
  "Swagger.Endpoint.User.Delete.Summary": "Delete user",
  "Swagger.Endpoint.User.Activate.Summary": "Activate user",
  "Swagger.Endpoint.User.Deactivate.Summary": "Deactivate user",
  "Swagger.Endpoint.User.BulkUpload.Summary": "Bulk upload users",

  "Swagger.Endpoint.UserPreferences.GetAll.Summary": "Get all user preferences",
  "Swagger.Endpoint.UserPreferences.GetPaged.Summary": "Get user preferences paged",
  "Swagger.Endpoint.UserPreferences.GetById.Summary": "Get user preferences by ID",
  "Swagger.Endpoint.UserPreferences.Create.Summary": "Create new user preferences",
  "Swagger.Endpoint.UserPreferences.Update.Summary": "Update user preferences",
  "Swagger.Endpoint.UserPreferences.Delete.Summary": "Delete user preferences",
  "Swagger.Endpoint.UserPreferences.GetByUser.Summary": "Get user preferences by user",
  "Swagger.Endpoint.UserPreferences.Activate.Summary": "Activate user preferences",
  "Swagger.Endpoint.UserPreferences.Deactivate.Summary": "Deactivate user preferences",

  "Swagger.Endpoint.UserRole.GetAll.Summary": "Get all user-role associations",
  "Swagger.Endpoint.UserRole.GetById.Summary": "Get user-role association by ID",
  "Swagger.Endpoint.UserRole.Delete.Summary": "Delete user-role association",
  "Swagger.Endpoint.UserRole.GetByUser.Summary": "Get associations by user",
  "Swagger.Endpoint.UserRole.GetByRole.Summary": "Get associations by role",
  "Swagger.Endpoint.UserRole.Create.Summary": "Create new user-role association",
  "Swagger.Endpoint.UserRole.Update.Summary": "Update user-role association",
  "Swagger.Endpoint.UserRole.BulkUpload.Summary": "Bulk upload user-role associations",

  "Swagger.Endpoint.RolePermission.GetAll.Summary": "Get all role permissions",
  "Swagger.Endpoint.RolePermission.Create.Summary": "Create new role permission",
  "Swagger.Endpoint.RolePermission.GetById.Summary": "Get role permission by ID",
  "Swagger.Endpoint.RolePermission.Delete.Summary": "Delete role permission",
  "Swagger.Endpoint.RolePermission.GetByRole.Summary": "Get permissions by role",
  "Swagger.Endpoint.RolePermission.GetByResource.Summary": "Get permissions by resource",
  "Swagger.Endpoint.RolePermission.BulkUpload.Summary": "Bulk upload role permissions",

  "Swagger.Endpoint.Job.GetById.Summary": "Get job by ID",
  "Swagger.Endpoint.Job.Update.Summary": "Update job",
  "Swagger.Endpoint.Job.Delete.Summary": "Delete job",
  "Swagger.Endpoint.Job.GetPaged.Summary": "Get paged jobs",
  "Swagger.Endpoint.Job.Create.Summary": "Create new job",
  "Swagger.Endpoint.Job.Activate.Summary": "Activate job",
  "Swagger.Endpoint.Job.Deactivate.Summary": "Deactivate job",
  "Swagger.Endpoint.Job.Execute.Summary": "Execute job",

  "Swagger.Endpoint.JwtKey.GetJwtKeysByTenant.Summary": "Get JWT keys by tenant",
  "Swagger.Endpoint.JwtKey.GetActiveJwtKey.Summary": "Get active JWT key",
  "Swagger.Endpoint.JwtKey.CreateInitialJwtKey.Summary": "Create initial JWT key",
  "Swagger.Endpoint.JwtKey.RevokeJwtKey.Summary": "Revoke JWT key",

  "Swagger.Response.200.Description": "Success",
  "Swagger.Response.201.Description": "Created",
  "Swagger.Response.204.Description": "No Content",
  "Swagger.Response.400.Description": "Bad Request",
  "Swagger.Response.401.Description": "Unauthorized",
  "Swagger.Response.403.Description": "Forbidden",
  "Swagger.Response.404.Description": "Not Found",
  "Swagger.Response.409.Description": "Conflict",
  "Swagger.Response.410.Description": "Gone",
  "Swagger.Response.500.Description": "Internal Server Error",

  "Swagger.Endpoint.AddressType.GetAll.Summary": "Get all address types",
  "Swagger.Endpoint.AddressType.GetPaged.Summary": "Get address types paged",
  "Swagger.Endpoint.AddressType.GetById.Summary": "Get address type by ID",
  "Swagger.Endpoint.AddressType.Create.Summary": "Create new address type",
  "Swagger.Endpoint.AddressType.Update.Summary": "Update address type",
  "Swagger.Endpoint.AddressType.Delete.Summary": "Delete address type",
  "Swagger.Endpoint.AddressType.Activate.Summary": "Activate address type",
  "Swagger.Endpoint.AddressType.Deactivate.Summary": "Deactivate address type",
  "Swagger.Endpoint.AddressType.BulkUpload.Summary": "Bulk upload address types",
  "Swagger.Endpoint.ClientType.GetAll.Summary": "Get all client types",
  "Swagger.Endpoint.ClientType.GetPaged.Summary": "Get client types paged",
  "Swagger.Endpoint.ClientType.GetById.Summary": "Get client type by ID",
  "Swagger.Endpoint.ClientType.Create.Summary": "Create new client type",
  "Swagger.Endpoint.ClientType.Update.Summary": "Update client type",
  "Swagger.Endpoint.ClientType.Delete.Summary": "Delete client type",
  "Swagger.Endpoint.ClientType.Activate.Summary": "Activate client type",
  "Swagger.Endpoint.ClientType.Deactivate.Summary": "Deactivate client type",
  "Swagger.Endpoint.ClientType.BulkUpload.Summary": "Bulk upload client types",
  "Swagger.Endpoint.ConsentType.GetAll.Summary": "Get all consent types",
  "Swagger.Endpoint.ConsentType.GetPaged.Summary": "Get consent types paged",
  "Swagger.Endpoint.ConsentType.GetById.Summary": "Get consent type by ID",
  "Swagger.Endpoint.ConsentType.Create.Summary": "Create new consent type",
  "Swagger.Endpoint.ConsentType.Update.Summary": "Update consent type",
  "Swagger.Endpoint.ConsentType.Delete.Summary": "Delete consent type",
  "Swagger.Endpoint.ConsentType.Activate.Summary": "Activate consent type",
  "Swagger.Endpoint.ConsentType.Deactivate.Summary": "Deactivate consent type",
  "Swagger.Endpoint.ConsentType.BulkUpload.Summary": "Bulk upload consent types",

  "Swagger.Endpoint.ClientAddress.GetAll.Summary": "Get all client addresses",
  "Swagger.Endpoint.ClientAddress.GetPaged.Summary": "Get client addresses paged",
  "Swagger.Endpoint.ClientAddress.GetById.Summary": "Get client address by ID",
  "Swagger.Endpoint.ClientAddress.Create.Summary": "Create new client address",
  "Swagger.Endpoint.ClientAddress.Update.Summary": "Update client address",
  "Swagger.Endpoint.ClientAddress.Delete.Summary": "Delete client address",
  "Swagger.Endpoint.ClientAddress.Activate.Summary": "Activate client address",
  "Swagger.Endpoint.ClientAddress.Deactivate.Summary": "Deactivate client address",
  "Swagger.Endpoint.ClientAddress.BulkUpload.Summary": "Bulk upload client addresses",

  "Swagger.Endpoint.ClientContact.GetAll.Summary": "Get all client contacts",
  "Swagger.Endpoint.ClientContact.GetPaged.Summary": "Get client contacts paged",
  "Swagger.Endpoint.ClientContact.GetById.Summary": "Get client contact by ID",
  "Swagger.Endpoint.ClientContact.Create.Summary": "Create new client contact",
  "Swagger.Endpoint.ClientContact.Update.Summary": "Update client contact",
  "Swagger.Endpoint.ClientContact.Delete.Summary": "Delete client contact",
  "Swagger.Endpoint.ClientContact.Activate.Summary": "Activate client contact",
  "Swagger.Endpoint.ClientContact.Deactivate.Summary": "Deactivate client contact",
  "Swagger.Endpoint.ClientContact.BulkUpload.Summary": "Bulk upload client contacts",

  "Swagger.Endpoint.Client.GetAll.Summary": "Get all clients",
  "Swagger.Endpoint.Client.Create.Summary": "Create new client",
  "Swagger.Endpoint.Client.GetById.Summary": "Get client by ID",
  "Swagger.Endpoint.Client.Update.Summary": "Update client",
  "Swagger.Endpoint.Client.Delete.Summary": "Delete client",
  "Swagger.Endpoint.Client.GetPaged.Summary": "Get clients paged",
  "Swagger.Endpoint.Client.Activate.Summary": "Activate client",
  "Swagger.Endpoint.Client.Deactivate.Summary": "Deactivate client",
  "Swagger.Endpoint.Client.BulkUpload.Summary": "Bulk upload clients",

  "Swagger.Endpoint.Team.GetAll.Summary": "Get all teams",
  "Swagger.Endpoint.Team.Create.Summary": "Create new team",
  "Swagger.Endpoint.Team.GetById.Summary": "Get team by ID",
  "Swagger.Endpoint.Team.Update.Summary": "Update team",
  "Swagger.Endpoint.Team.Delete.Summary": "Delete team",
  "Swagger.Endpoint.Team.GetPaged.Summary": "Get teams paged",
  "Swagger.Endpoint.Team.Activate.Summary": "Activate team",
  "Swagger.Endpoint.Team.Deactivate.Summary": "Deactivate team",
  "Swagger.Endpoint.Team.BulkUpload.Summary": "Bulk upload teams",

  "Swagger.Endpoint.Visit.GetAll.Summary": "Get all visits",
  "Swagger.Endpoint.Visit.GetPaged.Summary": "Get visits paged",
  "Swagger.Endpoint.Visit.GetById.Summary": "Get visit by ID",
  "Swagger.Endpoint.Visit.Create.Summary": "Create new visit",
  "Swagger.Endpoint.Visit.Update.Summary": "Update visit",
  "Swagger.Endpoint.Visit.Delete.Summary": "Delete visit",
  "Swagger.Endpoint.Visit.Activate.Summary": "Activate visit",
  "Swagger.Endpoint.Visit.Deactivate.Summary": "Deactivate visit",
  "Swagger.Endpoint.Visit.BulkUpload.Summary": "Bulk upload visits",

  "Swagger.Endpoint.VisitAddress.GetAll.Summary": "Get all visit addresses",
  "Swagger.Endpoint.VisitAddress.GetPaged.Summary": "Get visit addresses paged",
  "Swagger.Endpoint.VisitAddress.GetById.Summary": "Get visit address by ID",
  "Swagger.Endpoint.VisitAddress.Create.Summary": "Create new visit address",
  "Swagger.Endpoint.VisitAddress.Update.Summary": "Update visit address",
  "Swagger.Endpoint.VisitAddress.Activate.Summary": "Activate visit address",
  "Swagger.Endpoint.VisitAddress.Deactivate.Summary": "Deactivate visit address",
  "Swagger.Endpoint.VisitAddress.Delete.Summary": "Delete visit address",
  "Swagger.Endpoint.VisitAddress.BulkUpload.Summary": "Bulk upload visit addresses",

  "Swagger.Endpoint.Status.GetAll.Summary": "Get all visit statuses",
  "Swagger.Endpoint.Status.GetPaged.Summary": "Get visit statuses paged",
  "Swagger.Endpoint.Status.GetById.Summary": "Get visit status by ID",
  "Swagger.Endpoint.Status.Create.Summary": "Create new visit status",
  "Swagger.Endpoint.Status.Update.Summary": "Update visit status",
  "Swagger.Endpoint.Status.Delete.Summary": "Delete visit status",
  "Swagger.Endpoint.Status.Activate.Summary": "Activate visit status",
  "Swagger.Endpoint.Status.Deactivate.Summary": "Deactivate visit status",
  "Swagger.Endpoint.Status.BulkUpload.Summary": "Bulk upload visit statuses",

  "Swagger.Endpoint.StatusType.GetAll.Summary": "Get all status types",
  "Swagger.Endpoint.StatusType.GetPaged.Summary": "Get paged status types",
  "Swagger.Endpoint.StatusType.GetById.Summary": "Get status type by ID",
  "Swagger.Endpoint.StatusType.Create.Summary": "Create new status type",
  "Swagger.Endpoint.StatusType.Update.Summary": "Update status type",
  "Swagger.Endpoint.StatusType.Delete.Summary": "Delete status type",
  "Swagger.Endpoint.StatusType.Activate.Summary": "Activate status type",
  "Swagger.Endpoint.StatusType.Deactivate.Summary": "Deactivate status type",
  "Swagger.Endpoint.StatusType.BulkUpload.Summary": "Bulk upload status types",

  "Swagger.Endpoint.VisitContact.GetAll.Summary": "Get all visit contacts",
  "Swagger.Endpoint.VisitContact.GetPaged.Summary": "Get visit contacts paged",
  "Swagger.Endpoint.VisitContact.GetById.Summary": "Get visit contact by ID",
  "Swagger.Endpoint.VisitContact.Create.Summary": "Create new visit contact",
  "Swagger.Endpoint.VisitContact.Update.Summary": "Update visit contact",
  "Swagger.Endpoint.VisitContact.Activate.Summary": "Activate visit contact",
  "Swagger.Endpoint.VisitContact.Deactivate.Summary": "Deactivate visit contact",
  "Swagger.Endpoint.VisitContact.Delete.Summary": "Delete visit contact",
  "Swagger.Endpoint.VisitContact.BulkUpload.Summary": "Bulk upload visit contacts",

  "Swagger.Endpoint.TeamMembersTeams.GetAll.Summary": "Get all team-member associations",
  "Swagger.Endpoint.TeamMembersTeams.GetById.Summary": "Get team-member association by ID",
  "Swagger.Endpoint.TeamMembersTeams.Create.Summary": "Create new team-member association",
  "Swagger.Endpoint.TeamMembersTeams.Update.Summary": "Update team-member association",
  "Swagger.Endpoint.TeamMembersTeams.Delete.Summary": "Delete team-member association",
  "Swagger.Endpoint.TeamMembersTeams.GetPaged.Summary": "Get team-member associations paged",
  "Swagger.Endpoint.TeamMembersTeams.Activate.Summary": "Activate team-member association",
  "Swagger.Endpoint.TeamMembersTeams.Deactivate.Summary": "Deactivate team-member association",
  "Swagger.Endpoint.TeamMembersTeams.BulkUpload.Summary": "Bulk upload team-member associations",

  "Swagger.Endpoint.VisitTeamVehicle.GetAll.Summary": "Get all visit team vehicles",
  "Swagger.Endpoint.VisitTeamVehicle.GetPaged.Summary": "Get visit team vehicles paged",
  "Swagger.Endpoint.VisitTeamVehicle.GetById.Summary": "Get visit team vehicle by ID",
  "Swagger.Endpoint.VisitTeamVehicle.Create.Summary": "Create new visit team vehicle association",
  "Swagger.Endpoint.VisitTeamVehicle.Update.Summary": "Update visit team vehicle association",
  "Swagger.Endpoint.VisitTeamVehicle.Delete.Summary": "Delete visit team vehicle association",
  "Swagger.Endpoint.VisitTeamVehicle.Activate.Summary": "Activate visit team vehicle association",
  "Swagger.Endpoint.VisitTeamVehicle.Deactivate.Summary": "Deactivate visit team vehicle association",
  "Swagger.Endpoint.VisitTeamVehicle.BulkUpload.Summary": "Bulk upload visit team vehicle associations",

  "Swagger.Endpoint.VisitTeamEquipment.GetAll.Summary": "Get all visit team equipments",
  "Swagger.Endpoint.VisitTeamEquipment.GetPaged.Summary": "Get visit team equipments paged",
  "Swagger.Endpoint.VisitTeamEquipment.GetById.Summary": "Get visit team equipment by ID",
  "Swagger.Endpoint.VisitTeamEquipment.Create.Summary": "Create new visit team equipment association",
  "Swagger.Endpoint.VisitTeamEquipment.Update.Summary": "Update visit team equipment association",
  "Swagger.Endpoint.VisitTeamEquipment.Delete.Summary": "Delete visit team equipment association",
  "Swagger.Endpoint.VisitTeamEquipment.Activate.Summary": "Activate visit team equipment association",
  "Swagger.Endpoint.VisitTeamEquipment.Deactivate.Summary": "Deactivate visit team equipment association",
  "Swagger.Endpoint.VisitTeamEquipment.BulkUpload.Summary": "Bulk upload visit team equipment associations",

  "Swagger.Endpoint.Employee.GetAll.Summary": "Get all employees",
  "Swagger.Endpoint.Employee.GetById.Summary": "Get employee by ID",
  "Swagger.Endpoint.Employee.GetPaged.Summary": "Get employees paged",
  "Swagger.Endpoint.Employee.Create.Summary": "Create new employee",
  "Swagger.Endpoint.Employee.Update.Summary": "Update employee",
  "Swagger.Endpoint.Employee.Delete.Summary": "Delete employee",
  "Swagger.Endpoint.Employee.Activate.Summary": "Activate employee",
  "Swagger.Endpoint.Employee.Deactivate.Summary": "Deactivate employee",
  "Swagger.Endpoint.Employee.BulkUpload.Summary": "Bulk upload employees",

  "Swagger.Endpoint.EmployeeAddress.GetAll.Summary": "Get all employee addresses",
  "Swagger.Endpoint.EmployeeAddress.GetById.Summary": "Get employee address by ID",
  "Swagger.Endpoint.EmployeeAddress.GetPaged.Summary": "Get employee addresses paged",
  "Swagger.Endpoint.EmployeeAddress.Create.Summary": "Create new employee address",
  "Swagger.Endpoint.EmployeeAddress.Update.Summary": "Update employee address",
  "Swagger.Endpoint.EmployeeAddress.Delete.Summary": "Delete employee address",
  "Swagger.Endpoint.EmployeeAddress.Activate.Summary": "Activate employee address",
  "Swagger.Endpoint.EmployeeAddress.Deactivate.Summary": "Deactivate employee address",
  "Swagger.Endpoint.EmployeeAddress.BulkUpload.Summary": "Bulk upload employee addresses",

  "Swagger.Endpoint.EmployeeContact.GetAll.Summary": "Get all employee contacts",
  "Swagger.Endpoint.EmployeeContact.GetById.Summary": "Get employee contact by ID",
  "Swagger.Endpoint.EmployeeContact.GetPaged.Summary": "Get employee contacts paged",
  "Swagger.Endpoint.EmployeeContact.Create.Summary": "Create new employee contact",
  "Swagger.Endpoint.EmployeeContact.Update.Summary": "Update employee contact",
  "Swagger.Endpoint.EmployeeContact.Delete.Summary": "Delete employee contact",
  "Swagger.Endpoint.EmployeeContact.Activate.Summary": "Activate employee contact",
  "Swagger.Endpoint.EmployeeContact.Deactivate.Summary": "Deactivate employee contact",
  "Swagger.Endpoint.EmployeeContact.BulkUpload.Summary": "Bulk upload employee contacts",

  "Swagger.Endpoint.EmployeeTeams.GetAll.Summary": "Get all employee-team associations",
  "Swagger.Endpoint.EmployeeTeams.GetById.Summary": "Get employee-team association by ID",
  "Swagger.Endpoint.EmployeeTeams.GetPaged.Summary": "Get employee-team associations paged",
  "Swagger.Endpoint.EmployeeTeams.Create.Summary": "Create new employee-team association",
  "Swagger.Endpoint.EmployeeTeams.Update.Summary": "Update employee-team association",
  "Swagger.Endpoint.EmployeeTeams.Delete.Summary": "Delete employee-team association",
  "Swagger.Endpoint.EmployeeTeams.Activate.Summary": "Activate employee-team association",
  "Swagger.Endpoint.EmployeeTeams.Deactivate.Summary": "Deactivate employee-team association",
  "Swagger.Endpoint.EmployeeTeams.BulkUpload.Summary": "Bulk upload employee-team associations",

  "Swagger.Endpoint.ClientCompany.GetAll.Summary": "Get all client companies",
  "Swagger.Endpoint.ClientCompany.GetById.Summary": "Get client company by ID",
  "Swagger.Endpoint.ClientCompany.GetByClientId.Summary": "Get client company by client ID",
  "Swagger.Endpoint.ClientCompany.GetPaged.Summary": "Get client companies paged",
  "Swagger.Endpoint.ClientCompany.Create.Summary": "Create new client company",
  "Swagger.Endpoint.ClientCompany.Update.Summary": "Update client company",
  "Swagger.Endpoint.ClientCompany.Delete.Summary": "Delete client company",
  "Swagger.Endpoint.ClientCompany.Activate.Summary": "Activate client company",
  "Swagger.Endpoint.ClientCompany.Deactivate.Summary": "Deactivate client company",

  "Swagger.Endpoint.ClientIndividual.GetAll.Summary": "Get all individual clients",
  "Swagger.Endpoint.ClientIndividual.GetById.Summary": "Get individual client by ID",
  "Swagger.Endpoint.ClientIndividual.GetByClientId.Summary": "Get individual client by client ID",
  "Swagger.Endpoint.ClientIndividual.GetByDocument.Summary": "Get individual client by document",
  "Swagger.Endpoint.ClientIndividual.GetPaged.Summary": "Get individual clients paged",
  "Swagger.Endpoint.ClientIndividual.Create.Summary": "Create new individual client",
  "Swagger.Endpoint.ClientIndividual.Update.Summary": "Update individual client",
  "Swagger.Endpoint.ClientIndividual.Delete.Summary": "Delete individual client",
  "Swagger.Endpoint.ClientIndividual.Activate.Summary": "Activate individual client",
  "Swagger.Endpoint.ClientIndividual.Deactivate.Summary": "Deactivate individual client",

  "Swagger.Endpoint.ClientFiscalData.GetAll.Summary": "Get all individual client fiscal data",
  "Swagger.Endpoint.ClientFiscalData.GetActive.Summary": "Get active individual client fiscal data",
  "Swagger.Endpoint.ClientFiscalData.GetById.Summary": "Get individual client fiscal data by ID",
  "Swagger.Endpoint.ClientFiscalData.GetByClientIndividualId.Summary": "Get fiscal data by individual client ID",
  "Swagger.Endpoint.ClientFiscalData.GetPaged.Summary": "Get individual client fiscal data paged",
  "Swagger.Endpoint.ClientFiscalData.Create.Summary": "Create new individual client fiscal data",
  "Swagger.Endpoint.ClientFiscalData.Update.Summary": "Update individual client fiscal data",
  "Swagger.Endpoint.ClientFiscalData.Delete.Summary": "Delete individual client fiscal data",
  "Swagger.Endpoint.ClientFiscalData.Activate.Summary": "Activate individual client fiscal data",
  "Swagger.Endpoint.ClientFiscalData.Deactivate.Summary": "Deactivate individual client fiscal data",

  "Swagger.Endpoint.ClientConsents.GetAll.Summary": "Get all client consents",
  "Swagger.Endpoint.ClientConsents.GetById.Summary": "Get client consent by ID",
  "Swagger.Endpoint.ClientConsents.GetByClientId.Summary": "Get consents by client ID",
  "Swagger.Endpoint.ClientConsents.GetByConsentTypeId.Summary": "Get consents by consent type ID",
  "Swagger.Endpoint.ClientConsents.GetByClientAndConsentType.Summary": "Get consent by client and consent type",
  "Swagger.Endpoint.ClientConsents.GetPaged.Summary": "Get client consents paged",
  "Swagger.Endpoint.ClientConsents.Create.Summary": "Create new client consent",
  "Swagger.Endpoint.ClientConsents.Update.Summary": "Update client consent",
  "Swagger.Endpoint.ClientConsents.Delete.Summary": "Delete client consent",
  "Swagger.Endpoint.ClientConsents.Activate.Summary": "Activate client consent",
  "Swagger.Endpoint.ClientConsents.Deactivate.Summary": "Deactivate client consent",
  "Swagger.Endpoint.ClientConsents.Revoke.Summary": "Revoke client consent",
  "Swagger.Endpoint.ClientConsents.Grant.Summary": "Grant client consent",

  "Swagger.Endpoint.ClientHierarchy.GetAll.Summary": "Get all client hierarchies",
  "Swagger.Endpoint.ClientHierarchy.GetById.Summary": "Get client hierarchy by ID",
  "Swagger.Endpoint.ClientHierarchy.GetByParentClientId.Summary": "Get hierarchies by parent client ID",
  "Swagger.Endpoint.ClientHierarchy.GetByChildClientId.Summary": "Get hierarchies by child client ID",
  "Swagger.Endpoint.ClientHierarchy.GetPaged.Summary": "Get client hierarchies paged",
  "Swagger.Endpoint.ClientHierarchy.Create.Summary": "Create new client hierarchy",
  "Swagger.Endpoint.ClientHierarchy.Update.Summary": "Update client hierarchy",
  "Swagger.Endpoint.ClientHierarchy.Delete.Summary": "Delete client hierarchy",
  "Swagger.Endpoint.ClientHierarchy.Activate.Summary": "Activate client hierarchy",
  "Swagger.Endpoint.ClientHierarchy.Deactivate.Summary": "Deactivate client hierarchy",

  "Swagger.Endpoint.FileType.GetAll.Summary": "Get all file types",
  "Swagger.Endpoint.FileType.GetById.Summary": "Get file type by ID",
  "Swagger.Endpoint.FileType.GetPaged.Summary": "Get file types paged",
  "Swagger.Endpoint.FileType.Create.Summary": "Create new file type",
  "Swagger.Endpoint.FileType.Update.Summary": "Update file type",
  "Swagger.Endpoint.FileType.Delete.Summary": "Delete file type",
  "Swagger.Endpoint.FileType.Activate.Summary": "Activate file type",
  "Swagger.Endpoint.FileType.Deactivate.Summary": "Deactivate file type",
  "Swagger.Endpoint.FileType.BulkUpload.Summary": "Bulk upload file types",

  "Swagger.Endpoint.OriginType.GetAll.Summary": "Get all origin types",
  "Swagger.Endpoint.OriginType.GetById.Summary": "Get origin type by ID",
  "Swagger.Endpoint.OriginType.GetPaged.Summary": "Get origin types paged",
  "Swagger.Endpoint.OriginType.Create.Summary": "Create new origin type",
  "Swagger.Endpoint.OriginType.Update.Summary": "Update origin type",
  "Swagger.Endpoint.OriginType.Delete.Summary": "Delete origin type",
  "Swagger.Endpoint.OriginType.Activate.Summary": "Activate origin type",
  "Swagger.Endpoint.OriginType.Deactivate.Summary": "Deactivate origin type",

  "Swagger.Endpoint.VisitAttachment.GetAll.Summary": "Get all visit attachments",
  "Swagger.Endpoint.VisitAttachment.GetById.Summary": "Get visit attachment by ID",
  "Swagger.Endpoint.VisitAttachment.GetByPublicId.Summary": "Get visit attachment by public ID",
  "Swagger.Endpoint.VisitAttachment.GetByVisitId.Summary": "Get attachments by visit ID",
  "Swagger.Endpoint.VisitAttachment.GetByCategoryId.Summary": "Get attachments by category ID",
  "Swagger.Endpoint.VisitAttachment.GetPrimaryByVisitId.Summary": "Get primary attachment by visit ID",
  "Swagger.Endpoint.VisitAttachment.GetPaged.Summary": "Get visit attachments paged",
  "Swagger.Endpoint.VisitAttachment.Create.Summary": "Create new visit attachment",
  "Swagger.Endpoint.VisitAttachment.Update.Summary": "Update visit attachment",
  "Swagger.Endpoint.VisitAttachment.Delete.Summary": "Delete visit attachment",
  "Swagger.Endpoint.VisitAttachment.Activate.Summary": "Activate visit attachment",
  "Swagger.Endpoint.VisitAttachment.Deactivate.Summary": "Deactivate visit attachment",
  "Swagger.Endpoint.VisitAttachment.SetAsPrimary.Summary": "Set as primary attachment",

  "Swagger.Endpoint.VisitTeamEmployee.GetAll.Summary": "Get all visit team employees",
  "Swagger.Endpoint.VisitTeamEmployee.GetById.Summary": "Get visit team employee by ID",
  "Swagger.Endpoint.VisitTeamEmployee.GetByVisitTeamId.Summary": "Get employees by visit team ID",
  "Swagger.Endpoint.VisitTeamEmployee.GetByEmployeeId.Summary": "Get visit teams by employee ID",
  "Swagger.Endpoint.VisitTeamEmployee.GetActiveByVisitTeamId.Summary": "Get active employees by visit team ID",
  "Swagger.Endpoint.VisitTeamEmployee.GetPaged.Summary": "Get visit team employees paged",
  "Swagger.Endpoint.VisitTeamEmployee.Create.Summary": "Create new visit team employee",
  "Swagger.Endpoint.VisitTeamEmployee.Update.Summary": "Update visit team employee",
  "Swagger.Endpoint.VisitTeamEmployee.Delete.Summary": "Delete visit team employee",
  "Swagger.Endpoint.VisitTeamEmployee.Activate.Summary": "Activate visit team employee",
  "Swagger.Endpoint.VisitTeamEmployee.Deactivate.Summary": "Deactivate visit team employee",

  "Swagger.Endpoint.VisitTeams.GetAll.Summary": "Get all visit teams",
  "Swagger.Endpoint.VisitTeams.GetById.Summary": "Get visit team by ID",
  "Swagger.Endpoint.VisitTeams.GetPaged.Summary": "Get visit teams paged",
  "Swagger.Endpoint.VisitTeams.Create.Summary": "Create new visit team",
  "Swagger.Endpoint.VisitTeams.Update.Summary": "Update visit team",
  "Swagger.Endpoint.VisitTeams.Delete.Summary": "Delete visit team",
  "Swagger.Endpoint.VisitTeams.Activate.Summary": "Activate visit team",
  "Swagger.Endpoint.VisitTeams.Deactivate.Summary": "Deactivate visit team",
  "Swagger.Endpoint.VisitTeams.BulkUpload.Summary": "Bulk upload visit teams",

  "Swagger.Endpoint.AttachmentCategory.GetAll.Summary": "Get all attachment categories",
  "Swagger.Endpoint.AttachmentCategory.GetActive.Summary": "Get active attachment categories",
  "Swagger.Endpoint.AttachmentCategory.GetById.Summary": "Get attachment category by ID",
  "Swagger.Endpoint.AttachmentCategory.GetPaged.Summary": "Get attachment categories paged",
  "Swagger.Endpoint.AttachmentCategory.Create.Summary": "Create new attachment category",
  "Swagger.Endpoint.AttachmentCategory.Update.Summary": "Update attachment category",
  "Swagger.Endpoint.AttachmentCategory.Delete.Summary": "Delete attachment category",
  "Swagger.Endpoint.AttachmentCategory.Activate.Summary": "Activate attachment category",
  "Swagger.Endpoint.AttachmentCategory.Deactivate.Summary": "Deactivate attachment category",
  "Swagger.Endpoint.AttachmentCategory.BulkUpload.Summary": "Bulk upload attachment categories"
}